transpolibre/__init__.py
transpolibre/_version.py
transpolibre/main.py
transpolibre/py.typed
transpolibre/lib/__init__.py
transpolibre/lib/get_lang_name.py
transpolibre/lib/parse_arguments.py
transpolibre/lib/qt_translator.py
transpolibre/lib/trans_list.py
transpolibre/lib/trans_local.py
transpolibre/lib/trans_msg.py
transpolibre/lib/trans_ollama.py
transpolibre/lib/trans_pofile.py
transpolibre/lib/trans_tsfile.py
transpolibre/lib/trans_tsfile_local.py
transpolibre/lib/trans_tsfile_ollama.py
transpolibre/lib/update_pofile.py
transpolibre-0.8.15.dist-info/licenses/LICENSE-CC.txt
transpolibre-0.8.15.dist-info/licenses/LICENSE-apache.txt
transpolibre-0.8.15.dist-info/METADATA
transpolibre-0.8.15.dist-info/WHEEL
transpolibre-0.8.15.dist-info/entry_points.txt
transpolibre-0.8.15.dist-info/top_level.txt
transpolibre-0.8.15.dist-info/RECORD
