Metadata-Version: 2.4
Name: transpolibre
Version: 0.8.15
Summary: Automate translation of gettext PO files using LibreTranslate, Ollama, and local models
Author-email: Jeff Moe <moe@spacecruft.org>
License: Apache-2.0
Project-URL: Homepage, https://transpolibre.org
Project-URL: Documentation, https://transpolibre.org
Project-URL: Repository, https://spacecruft.org/deepcrayon/transpolibre
Project-URL: Issues, https://spacecruft.org/deepcrayon/transpolibre
Project-URL: Changelog, https://spacecruft.org/deepcrayon/transpolibre/raw/branch/main/CHANGELOG.txt
Keywords: gettext,i18n,l10n,internationalization,libretranslate,localization,ollama,machine-translation,pofiles,po-files,python,pytorch,sphinx,text-processing,torch,translation
Classifier: Development Status :: 4 - Beta
Classifier: Environment :: Console
Classifier: Intended Audience :: Developers
Classifier: License :: OSI Approved :: Apache Software License
Classifier: Natural Language :: Arabic
Classifier: Natural Language :: Bengali
Classifier: Natural Language :: Chinese (Simplified)
Classifier: Natural Language :: English
Classifier: Natural Language :: French
Classifier: Natural Language :: German
Classifier: Natural Language :: Hindi
Classifier: Natural Language :: Indonesian
Classifier: Natural Language :: Italian
Classifier: Natural Language :: Japanese
Classifier: Natural Language :: Korean
Classifier: Natural Language :: Polish
Classifier: Natural Language :: Portuguese
Classifier: Natural Language :: Russian
Classifier: Natural Language :: Spanish
Classifier: Natural Language :: Turkish
Classifier: Operating System :: OS Independent
Classifier: Programming Language :: Python :: 3
Classifier: Topic :: Documentation :: Sphinx
Classifier: Topic :: Scientific/Engineering :: Artificial Intelligence
Classifier: Topic :: Software Development
Classifier: Topic :: Software Development :: Documentation
Classifier: Topic :: Software Development :: Internationalization
Classifier: Topic :: Software Development :: Localization
Classifier: Topic :: Text Processing :: Linguistic
Requires-Python: >=3.9
License-File: LICENSE-CC.txt
License-File: LICENSE-apache.txt
Requires-Dist: libretranslatepy
Requires-Dist: polib
Requires-Dist: pycountry
Requires-Dist: python-dotenv
Requires-Dist: requests
Requires-Dist: translate-toolkit>=3.10.0
Provides-Extra: all
Requires-Dist: libretranslatepy; extra == "all"
Requires-Dist: torch; extra == "all"
Requires-Dist: transformers; extra == "all"
Requires-Dist: accelerate; extra == "all"
Requires-Dist: bitsandbytes; extra == "all"
Requires-Dist: ollama; extra == "all"
Requires-Dist: protobuf; extra == "all"
Provides-Extra: dev
Requires-Dist: black; extra == "dev"
Requires-Dist: dead; extra == "dev"
Requires-Dist: mypy; extra == "dev"
Requires-Dist: ruff; extra == "dev"
Requires-Dist: setuptools-scm; extra == "dev"
Requires-Dist: sphinx; extra == "dev"
Requires-Dist: sphinx-autobuild; extra == "dev"
Requires-Dist: sphinx-autodoc-typehints; extra == "dev"
Requires-Dist: sphinx-intl; extra == "dev"
Requires-Dist: sphinx-notfound-page; extra == "dev"
Requires-Dist: sphinx-rtd-theme; extra == "dev"
Requires-Dist: sphinxcontrib-markdown; extra == "dev"
Requires-Dist: twine; extra == "dev"
Requires-Dist: types-polib; extra == "dev"
Requires-Dist: vulture; extra == "dev"
Provides-Extra: test
Requires-Dist: pytest>=7.0.0; extra == "test"
Requires-Dist: pytest-cov>=4.0.0; extra == "test"
Requires-Dist: pytest-mock>=3.10.0; extra == "test"
Requires-Dist: pytest-asyncio>=0.21.0; extra == "test"
Requires-Dist: pytest-timeout>=2.1.0; extra == "test"
Requires-Dist: pytest-xdist>=3.0.0; extra == "test"
Requires-Dist: hypothesis>=6.0.0; extra == "test"
Requires-Dist: faker>=18.0.0; extra == "test"
Requires-Dist: responses>=0.23.0; extra == "test"
Requires-Dist: freezegun>=1.2.0; extra == "test"
Provides-Extra: local
Requires-Dist: torch; extra == "local"
Requires-Dist: transformers; extra == "local"
Requires-Dist: accelerate; extra == "local"
Requires-Dist: bitsandbytes; extra == "local"
Provides-Extra: ollama
Requires-Dist: ollama; extra == "ollama"
Requires-Dist: protobuf; extra == "ollama"
Dynamic: license-file
